docufy/__init__.py
docufy/ai_analysis.py
docufy/generate_readme.py
docufy/utils.py
docufy-1.3.2.dist-info/licenses/LICENSE
docufy-1.3.2.dist-info/METADATA
docufy-1.3.2.dist-info/WHEEL
docufy-1.3.2.dist-info/entry_points.txt
docufy-1.3.2.dist-info/top_level.txt
docufy-1.3.2.dist-info/RECORD
