Metadata-Version: 2.4
Name: docufy
Version: 1.3.2
Summary: Generate a README from your project files using LLM
Author-email: Anozie Joel <dev@0xagbero.pw>
License: MIT
Requires-Python: >=3.8
License-File: LICENSE
Requires-Dist: google-generativeai>=0.4.1
Requires-Dist: python-dotenv>=1.0.0
Dynamic: license-file
